{"annotation-data-version":"2019-06-01 04:11:25","methods":[{"method":"Resnik (symmetric)","results":[{"itemid":"ORPHA:2818","score":0.6859422442179666,"itemname":"Spastic paraplegia-glaucoma-intellectual disability syndrome","rank":1.0},{"itemid":"ORPHA:101004","score":0.6734040230690512,"itemname":"Autosomal recessive spastic paraplegia type 24","rank":2.0},{"itemid":"ORPHA:726","score":0.6566780656174623,"itemname":"Alpers-Huttenlocher syndrome","rank":3.0},{"itemid":"ORPHA:98673","score":0.6513798117299394,"itemname":"Autosomal dominant optic atrophy, classic form","rank":4.0},{"itemid":"ORPHA:401800","score":0.6500698547063815,"itemname":"Autosomal recessive spastic paraplegia type 60","rank":5.0},{"itemid":"ORPHA:2815","score":0.6495683973413593,"itemname":"Spastic paraparesis-deafness syndrome","rank":6.0},{"itemid":"ORPHA:401795","score":0.6354399394428845,"itemname":"Autosomal recessive spastic paraplegia type 59","rank":7.0},{"itemid":"ORPHA:506353","score":0.6331704804680698,"itemname":"Autosomal recessive complex spastic paraplegia due to Kennedy pathway dysfunction","rank":8.0},{"itemid":"ORPHA:101010","score":0.6258916450974361,"itemname":"Autosomal spastic paraplegia type 30","rank":9.0},{"itemid":"ORPHA:140989","score":0.6251447923612835,"itemname":"Primary angiitis of the central nervous system","rank":10.0},{"itemid":"ORPHA:209967","score":0.6231620413100472,"itemname":"Episodic ataxia type 6","rank":11.0},{"itemid":"ORPHA:101007","score":0.6197918229354267,"itemname":"Autosomal recessive spastic paraplegia type 27","rank":12.0},{"itemid":"ORPHA:100986","score":0.617449731097639,"itemname":"Autosomal recessive spastic paraplegia type 5A","rank":13.0},{"itemid":"ORPHA:293168","score":0.61400018624487,"itemname":"Infantile-onset ascending hereditary spastic paralysis","rank":14.0},{"itemid":"ORPHA:139480","score":0.613895915775688,"itemname":"Autosomal recessive spastic paraplegia type 39","rank":15.0},{"itemid":"ORPHA:43","score":0.6104291577135724,"itemname":"X-linked adrenoleukodystrophy","rank":16.0},{"itemid":"ORPHA:685","score":0.6100009964263339,"itemname":"Hereditary spastic paraplegia","rank":17.0},{"itemid":"ORPHA:320375","score":0.6060864385252102,"itemname":"Autosomal recessive spastic paraplegia type 55","rank":18.0},{"itemid":"ORPHA:401830","score":0.604593167292693,"itemname":"Autosomal recessive spastic paraplegia type 69","rank":19.0},{"itemid":"ORPHA:845","score":0.6032356983696523,"itemname":"Tay-Sachs disease","rank":20.0},{"itemid":"ORPHA:459056","score":0.5986632640512246,"itemname":"Autosomal recessive spastic paraplegia type 75","rank":21.0},{"itemid":"ORPHA:251282","score":0.5984949712763146,"itemname":"Autosomal dominant spastic ataxia type 1","rank":22.0},{"itemid":"ORPHA:329308","score":0.597432805329034,"itemname":"Fatty acid hydroxylase-associated neurodegeneration","rank":23.0},{"itemid":"ORPHA:67047","score":0.5966801432461688,"itemname":"3-methylglutaconic aciduria type 3","rank":24.0},{"itemid":"ORPHA:100994","score":0.5961103929086649,"itemname":"Autosomal dominant spastic paraplegia type 13","rank":25.0},{"itemid":"ORPHA:53583","score":0.5904774754372885,"itemname":"Paroxysmal dystonic choreathetosis with episodic ataxia and spasticity","rank":26.0},{"itemid":"ORPHA:320396","score":0.5884624703487307,"itemname":"Autosomal recessive spastic paraplegia type 45","rank":27.0},{"itemid":"ORPHA:506","score":0.5838908047070595,"itemname":"Leigh syndrome","rank":28.0},{"itemid":"ORPHA:79135","score":0.5802351944048932,"itemname":"Episodic ataxia type 3","rank":29.0},{"itemid":"ORPHA:95433","score":0.577088182969696,"itemname":"Autosomal recessive spinocerebellar ataxia-blindness-deafness syndrome","rank":30.0},{"itemid":"ORPHA:254343","score":0.5740989313412378,"itemname":"Autosomal recessive spastic ataxia-optic atrophy-dysarthria syndrome","rank":31.0},{"itemid":"ORPHA:1910","score":0.5722586718750285,"itemname":"Fetal iodine syndrome","rank":32.0},{"itemid":"ORPHA:100989","score":0.5712505146946937,"itemname":"Autosomal dominant spastic paraplegia type 8","rank":33.0},{"itemid":"ORPHA:65","score":0.5697916571709555,"itemname":"Leber congenital amaurosis","rank":34.0},{"itemid":"ORPHA:3208","score":0.56908644202239,"itemname":"Isolated succinate-CoQ reductase deficiency","rank":35.0},{"itemid":"ORPHA:2406","score":0.5673463463600477,"itemname":"Locked-in syndrome","rank":36.0},{"itemid":"ORPHA:320355","score":0.56496426476549,"itemname":"Autosomal dominant spastic paraplegia type 41","rank":37.0},{"itemid":"ORPHA:171863","score":0.5638436812904549,"itemname":"Autosomal dominant spastic paraplegia type 42","rank":38.0},{"itemid":"ORPHA:3129","score":0.5614428699344923,"itemname":"Sarcosinemia","rank":39.0},{"itemid":"ORPHA:99857","score":0.5554223959663708,"itemname":"Secondary syringomyelia","rank":40.0},{"itemid":"ORPHA:468661","score":0.5544569465478408,"itemname":"Autosomal recessive spastic paraplegia type 74","rank":41.0},{"itemid":"ORPHA:444099","score":0.5527459089361678,"itemname":"Autosomal dominant spastic paraplegia type 73","rank":42.0},{"itemid":"ORPHA:464282","score":0.5526886846023937,"itemname":"Spastic paraplegia-severe developmental delay-epilepsy syndrome","rank":43.0},{"itemid":"ORPHA:357043","score":0.5518476378909732,"itemname":"Amyotrophic lateral sclerosis type 4","rank":44.0},{"itemid":"ORPHA:97","score":0.5496390613581065,"itemname":"Familial paroxysmal ataxia","rank":45.0},{"itemid":"ORPHA:513436","score":0.5491886537204446,"itemname":"Autosomal recessive spastic paraplegia type 78","rank":46.0},{"itemid":"ORPHA:275872","score":0.5488615723393728,"itemname":"Frontotemporal dementia with motor neuron disease","rank":47.0},{"itemid":"ORPHA:352641","score":0.5475420366163988,"itemname":"Autosomal recessive cerebellar ataxia with late-onset spasticity","rank":48.0},{"itemid":"ORPHA:309256","score":0.5466072297229652,"itemname":"Metachromatic leukodystrophy, late infantile form","rank":49.0},{"itemid":"ORPHA:401840","score":0.5463237232145511,"itemname":"Autosomal recessive spastic paraplegia type 71","rank":50.0}]},{"method":"Resnik (asymmetric)","results":[{"itemid":"ORPHA:98673","score":1.0,"itemname":"Autosomal dominant optic atrophy, classic form","rank":1.0},{"itemid":"ORPHA:847","score":0.9568946247470473,"itemname":"Alpha-thalassemia-X-linked intellectual disability syndrome","rank":2.0},{"itemid":"ORPHA:478","score":0.8919184312634613,"itemname":"Kallmann syndrome","rank":3.0},{"itemid":"ORPHA:369929","score":0.8885605904228605,"itemname":"Primary hyperaldosteronism-seizures-neurological abnormalities syndrome","rank":4.0},{"itemid":"ORPHA:2815","score":0.8842792183990167,"itemname":"Spastic paraparesis-deafness syndrome","rank":5.5},{"itemid":"ORPHA:2710","score":0.8842792183990167,"itemname":"Oculodentodigital dysplasia","rank":5.5},{"itemid":"ORPHA:140989","score":0.8801860086608208,"itemname":"Primary angiitis of the central nervous system","rank":7.0},{"itemid":"ORPHA:43","score":0.8766859319711271,"itemname":"X-linked adrenoleukodystrophy","rank":8.0},{"itemid":"ORPHA:845","score":0.8661114658514202,"itemname":"Tay-Sachs disease","rank":9.0},{"itemid":"ORPHA:255241","score":0.8631961559672766,"itemname":"Leigh syndrome with leukodystrophy","rank":11.0},{"itemid":"ORPHA:464282","score":0.8631961559672766,"itemname":"Spastic paraplegia-severe developmental delay-epilepsy syndrome","rank":11.0},{"itemid":"ORPHA:100986","score":0.8631961559672766,"itemname":"Autosomal recessive spastic paraplegia type 5A","rank":11.0},{"itemid":"ORPHA:33364","score":0.8631643858955551,"itemname":"Trichothiodystrophy","rank":13.0},{"itemid":"ORPHA:506353","score":0.8583381376846431,"itemname":"Autosomal recessive complex spastic paraplegia due to Kennedy pathway dysfunction","rank":14.5},{"itemid":"ORPHA:280763","score":0.8583381376846431,"itemname":"Severe intellectual disability and progressive spastic paraplegia","rank":14.5},{"itemid":"ORPHA:726","score":0.8504168298229013,"itemname":"Alpers-Huttenlocher syndrome","rank":16.5},{"itemid":"ORPHA:3208","score":0.8504168298229013,"itemname":"Isolated succinate-CoQ reductase deficiency","rank":16.5},{"itemid":"ORPHA:320375","score":0.8428235433950118,"itemname":"Autosomal recessive spastic paraplegia type 55","rank":18.0},{"itemid":"ORPHA:329308","score":0.8367494144513067,"itemname":"Fatty acid hydroxylase-associated neurodegeneration","rank":19.0},{"itemid":"ORPHA:99857","score":0.8351869887156627,"itemname":"Secondary syringomyelia","rank":20.0},{"itemid":"ORPHA:3129","score":0.8329407676712723,"itemname":"Sarcosinemia","rank":21.0},{"itemid":"ORPHA:2495","score":0.8293008318333747,"itemname":"Meningioma","rank":22.0},{"itemid":"ORPHA:3137","score":0.8230060905984674,"itemname":"Alpha-N-acetylgalactosaminidase deficiency","rank":23.0},{"itemid":"ORPHA:53583","score":0.8156345819478452,"itemname":"Paroxysmal dystonic choreathetosis with episodic ataxia and spasticity","rank":24.0},{"itemid":"ORPHA:101007","score":0.8055937931781535,"itemname":"Autosomal recessive spastic paraplegia type 27","rank":25.0},{"itemid":"ORPHA:100994","score":0.8015721234657032,"itemname":"Autosomal dominant spastic paraplegia type 13","rank":26.5},{"itemid":"ORPHA:401830","score":0.8015721234657032,"itemname":"Autosomal recessive spastic paraplegia type 69","rank":26.5},{"itemid":"ORPHA:487","score":0.8014173673651309,"itemname":"Krabbe disease","rank":28.5},{"itemid":"ORPHA:99027","score":0.8014173673651309,"itemname":"Adult-onset autosomal dominant leukodystrophy","rank":28.5},{"itemid":"ORPHA:209967","score":0.7973241576269352,"itemname":"Episodic ataxia type 6","rank":30.5},{"itemid":"ORPHA:117","score":0.7973241576269352,"itemname":"Behçet disease","rank":30.5},{"itemid":"ORPHA:309256","score":0.7950884563591952,"itemname":"Metachromatic leukodystrophy, late infantile form","rank":34.5},{"itemid":"ORPHA:309271","score":0.7950884563591952,"itemname":"Metachromatic leukodystrophy, adult form","rank":34.5},{"itemid":"ORPHA:300570","score":0.7950884563591952,"itemname":"Cortical dysgenesis with pontocerebellar hypoplasia due to TUBB3 mutation","rank":34.5},{"itemid":"ORPHA:95","score":0.7950884563591952,"itemname":"Friedreich ataxia","rank":34.5},{"itemid":"ORPHA:95433","score":0.7950884563591952,"itemname":"Autosomal recessive spinocerebellar ataxia-blindness-deafness syndrome","rank":34.5},{"itemid":"ORPHA:309263","score":0.7950884563591952,"itemname":"Metachromatic leukodystrophy, juvenile form","rank":34.5},{"itemid":"ORPHA:268943","score":0.7938240809372418,"itemname":"Unilateral polymicrogyria","rank":38.0},{"itemid":"ORPHA:83629","score":0.7936440391983538,"itemname":"Leukoencephalopathy-metaphyseal chondrodysplasia syndrome","rank":39.5},{"itemid":"ORPHA:468661","score":0.7936440391983538,"itemname":"Autosomal recessive spastic paraplegia type 74","rank":39.5},{"itemid":"ORPHA:65","score":0.7898353924183195,"itemname":"Leber congenital amaurosis","rank":42.0},{"itemid":"ORPHA:369950","score":0.7898353924183195,"itemname":"Intellectual disability-seizures-macrocephaly-obesity syndrome","rank":42.0},{"itemid":"ORPHA:828","score":0.7898353924183195,"itemname":"Stickler syndrome","rank":42.0},{"itemid":"ORPHA:67047","score":0.7857227313366121,"itemname":"3-methylglutaconic aciduria type 3","rank":44.0},{"itemid":"ORPHA:275872","score":0.7789987746724345,"itemname":"Frontotemporal dementia with motor neuron disease","rank":45.0},{"itemid":"ORPHA:98897","score":0.7767033104640741,"itemname":"Oculopharyngodistal myopathy","rank":46.0},{"itemid":"ORPHA:93474","score":0.7690640975996295,"itemname":"Scheie syndrome","rank":47.5},{"itemid":"ORPHA:93473","score":0.7690640975996295,"itemname":"Hurler syndrome","rank":47.5},{"itemid":"ORPHA:892","score":0.7682466691849831,"itemname":"Von Hippel-Lindau disease","rank":50.5},{"itemid":"ORPHA:1187","score":0.7682466691849831,"itemname":"Lethal ataxia with deafness and optic atrophy","rank":50.5}]},{"method":"Bernoulli with grid","results":[{"itemid":"ORPHA:2815","score":0.5407560275847585,"itemname":"Spastic paraparesis-deafness syndrome","rank":1.0},{"itemid":"ORPHA:98673","score":0.4592163274428548,"itemname":"Autosomal dominant optic atrophy, classic form","rank":2.0},{"itemid":"ORPHA:101004","score":2.453224647836257E-5,"itemname":"Autosomal recessive spastic paraplegia type 24","rank":3.0},{"itemid":"ORPHA:100986","score":1.382393814726614E-6,"itemname":"Autosomal recessive spastic paraplegia type 5A","rank":4.0},{"itemid":"ORPHA:101007","score":1.146542360850481E-6,"itemname":"Autosomal recessive spastic paraplegia type 27","rank":5.0},{"itemid":"ORPHA:53583","score":4.697080571465362E-7,"itemname":"Paroxysmal dystonic choreathetosis with episodic ataxia and spasticity","rank":6.0},{"itemid":"ORPHA:255241","score":7.667810840196309E-8,"itemname":"Leigh syndrome with leukodystrophy","rank":7.0},{"itemid":"ORPHA:845","score":2.5781145174785256E-8,"itemname":"Tay-Sachs disease","rank":8.0},{"itemid":"ORPHA:43","score":1.058424517786838E-8,"itemname":"X-linked adrenoleukodystrophy","rank":9.0},{"itemid":"ORPHA:487","score":3.0986622322571276E-10,"itemname":"Krabbe disease","rank":10.0},{"itemid":"ORPHA:464282","score":2.0101422227889127E-10,"itemname":"Spastic paraplegia-severe developmental delay-epilepsy syndrome","rank":11.0},{"itemid":"ORPHA:67047","score":1.6892822440018945E-10,"itemname":"3-methylglutaconic aciduria type 3","rank":12.0},{"itemid":"ORPHA:726","score":1.33922829975501E-10,"itemname":"Alpers-Huttenlocher syndrome","rank":13.0},{"itemid":"ORPHA:401830","score":6.811137902273674E-11,"itemname":"Autosomal recessive spastic paraplegia type 69","rank":14.0},{"itemid":"ORPHA:369929","score":5.1177697189876123E-11,"itemname":"Primary hyperaldosteronism-seizures-neurological abnormalities syndrome","rank":15.0},{"itemid":"ORPHA:100994","score":3.48925884081436E-11,"itemname":"Autosomal dominant spastic paraplegia type 13","rank":16.0},{"itemid":"ORPHA:99027","score":2.6795866139103747E-11,"itemname":"Adult-onset autosomal dominant leukodystrophy","rank":17.0},{"itemid":"ORPHA:2818","score":1.682793419268175E-11,"itemname":"Spastic paraplegia-glaucoma-intellectual disability syndrome","rank":18.0},{"itemid":"ORPHA:95433","score":1.3749026653113827E-11,"itemname":"Autosomal recessive spinocerebellar ataxia-blindness-deafness syndrome","rank":19.0},{"itemid":"ORPHA:506","score":6.743719811958079E-12,"itemname":"Leigh syndrome","rank":20.0},{"itemid":"ORPHA:1910","score":1.349695897030763E-12,"itemname":"Fetal iodine syndrome","rank":21.0},{"itemid":"ORPHA:329308","score":1.194213763563431E-12,"itemname":"Fatty acid hydroxylase-associated neurodegeneration","rank":22.0},{"itemid":"ORPHA:1368","score":8.874380905543305E-13,"itemname":"Cataract-ataxia-deafness syndrome","rank":23.0},{"itemid":"ORPHA:847","score":8.504208278066201E-13,"itemname":"Alpha-thalassemia-X-linked intellectual disability syndrome","rank":24.0},{"itemid":"ORPHA:2822","score":5.47996727913504E-13,"itemname":"Autosomal recessive spastic paraplegia type 11","rank":25.0},{"itemid":"ORPHA:101010","score":4.358933164306805E-13,"itemname":"Autosomal spastic paraplegia type 30","rank":26.0},{"itemid":"ORPHA:3129","score":2.607481740270282E-13,"itemname":"Sarcosinemia","rank":27.0},{"itemid":"ORPHA:217012","score":1.6425095663467827E-13,"itemname":"Spinocerebellar ataxia type 31","rank":28.0},{"itemid":"ORPHA:320401","score":1.1393997507885971E-13,"itemname":"Autosomal recessive spastic paraplegia type 44","rank":29.0},{"itemid":"ORPHA:459056","score":9.11992081608048E-14,"itemname":"Autosomal recessive spastic paraplegia type 75","rank":30.0},{"itemid":"ORPHA:1187","score":7.29991959806683E-14,"itemname":"Lethal ataxia with deafness and optic atrophy","rank":31.0},{"itemid":"ORPHA:309256","score":6.788901914185214E-14,"itemname":"Metachromatic leukodystrophy, late infantile form","rank":32.0},{"itemid":"ORPHA:401795","score":3.4771974360871355E-14,"itemname":"Autosomal recessive spastic paraplegia type 59","rank":33.5},{"itemid":"ORPHA:293168","score":3.4771974360871355E-14,"itemname":"Infantile-onset ascending hereditary spastic paralysis","rank":33.5},{"itemid":"ORPHA:251282","score":7.885054935624847E-15,"itemname":"Autosomal dominant spastic ataxia type 1","rank":35.0},{"itemid":"ORPHA:309263","score":7.88337602333567E-15,"itemname":"Metachromatic leukodystrophy, juvenile form","rank":36.0},{"itemid":"ORPHA:772","score":5.9783513606302915E-15,"itemname":"Infantile Refsum disease","rank":37.0},{"itemid":"ORPHA:401800","score":5.660230952349872E-15,"itemname":"Autosomal recessive spastic paraplegia type 60","rank":38.0},{"itemid":"ORPHA:95","score":4.217234395507149E-15,"itemname":"Friedreich ataxia","rank":39.0},{"itemid":"ORPHA:2406","score":3.8230871982392176E-15,"itemname":"Locked-in syndrome","rank":40.0},{"itemid":"ORPHA:702","score":1.0237895462219946E-15,"itemname":"Pelizaeus-Merzbacher disease","rank":41.0},{"itemid":"ORPHA:93474","score":6.828049777135999E-16,"itemname":"Scheie syndrome","rank":42.0},{"itemid":"ORPHA:506353","score":5.309090645715447E-16,"itemname":"Autosomal recessive complex spastic paraplegia due to Kennedy pathway dysfunction","rank":43.0},{"itemid":"ORPHA:101077","score":4.832890822962871E-16,"itemname":"X-linked Charcot-Marie-Tooth disease type 3","rank":44.5},{"itemid":"ORPHA:314911","score":4.832890822962871E-16,"itemname":"Severe Canavan disease","rank":44.5},{"itemid":"ORPHA:85336","score":4.3383233684690143E-16,"itemname":"X-linked neurodegenerative syndrome, Hamel type","rank":46.0},{"itemid":"ORPHA:2608","score":3.868446787464446E-16,"itemname":"N syndrome","rank":47.0},{"itemid":"ORPHA:478","score":3.511175646144243E-16,"itemname":"Kallmann syndrome","rank":48.0},{"itemid":"ORPHA:468661","score":2.807689091809394E-16,"itemname":"Autosomal recessive spastic paraplegia type 74","rank":49.0},{"itemid":"ORPHA:838","score":2.478781285499519E-16,"itemname":"Susac syndrome","rank":50.0}]},{"method":"Cosine Similarity","results":[{"itemid":"ORPHA:2818","score":0.7064172571013566,"itemname":"Spastic paraplegia-glaucoma-intellectual disability syndrome","rank":1.0},{"itemid":"ORPHA:101004","score":0.6600983619844495,"itemname":"Autosomal recessive spastic paraplegia type 24","rank":2.0},{"itemid":"ORPHA:2815","score":0.6064784348631226,"itemname":"Spastic paraparesis-deafness syndrome","rank":3.0},{"itemid":"ORPHA:85336","score":0.5925925925925926,"itemname":"X-linked neurodegenerative syndrome, Hamel type","rank":4.0},{"itemid":"ORPHA:53583","score":0.5895063447465633,"itemname":"Paroxysmal dystonic choreathetosis with episodic ataxia and spasticity","rank":5.0},{"itemid":"ORPHA:255","score":0.5871365639519862,"itemname":"Dopa-responsive dystonia","rank":6.0},{"itemid":"ORPHA:1910","score":0.5855400437691199,"itemname":"Fetal iodine syndrome","rank":7.0},{"itemid":"ORPHA:101007","score":0.5708992257184501,"itemname":"Autosomal recessive spastic paraplegia type 27","rank":8.0},{"itemid":"ORPHA:67047","score":0.561434614044346,"itemname":"3-methylglutaconic aciduria type 3","rank":9.0},{"itemid":"ORPHA:401795","score":0.5547001962252291,"itemname":"Autosomal recessive spastic paraplegia type 59","rank":10.5},{"itemid":"ORPHA:293168","score":0.5547001962252291,"itemname":"Infantile-onset ascending hereditary spastic paralysis","rank":10.5},{"itemid":"ORPHA:401800","score":0.5410017808004594,"itemname":"Autosomal recessive spastic paraplegia type 60","rank":12.0},{"itemid":"ORPHA:217012","score":0.5391291361472074,"itemname":"Spinocerebellar ataxia type 31","rank":13.0},{"itemid":"ORPHA:506","score":0.5389680556362955,"itemname":"Leigh syndrome","rank":14.0},{"itemid":"ORPHA:685","score":0.5360201681382464,"itemname":"Hereditary spastic paraplegia","rank":15.0},{"itemid":"ORPHA:256","score":0.5337605126836238,"itemname":"Early-onset generalized limb-onset dystonia","rank":16.5},{"itemid":"ORPHA:1949","score":0.5337605126836238,"itemname":"Benign familial neonatal epilepsy","rank":16.5},{"itemid":"ORPHA:726","score":0.517454889668201,"itemname":"Alpers-Huttenlocher syndrome","rank":18.0},{"itemid":"ORPHA:3175","score":0.5163977794943222,"itemname":"X-linked spasticity-intellectual disability-epilepsy syndrome","rank":19.0},{"itemid":"ORPHA:79323","score":0.5143444998736397,"itemname":"MPDU1-CDG","rank":20.5},{"itemid":"ORPHA:1368","score":0.5143444998736397,"itemname":"Cataract-ataxia-deafness syndrome","rank":20.5},{"itemid":"ORPHA:85297","score":0.5132002392796673,"itemname":"X-linked spinocerebellar ataxia type 3","rank":22.5},{"itemid":"ORPHA:357043","score":0.5132002392796673,"itemname":"Amyotrophic lateral sclerosis type 4","rank":22.5},{"itemid":"ORPHA:88644","score":0.5091750772173156,"itemname":"Autosomal recessive ataxia, Beauce type","rank":24.0},{"itemid":"ORPHA:2822","score":0.5053986957192689,"itemname":"Autosomal recessive spastic paraplegia type 11","rank":25.0},{"itemid":"ORPHA:401830","score":0.5051814855409226,"itemname":"Autosomal recessive spastic paraplegia type 69","rank":26.0},{"itemid":"ORPHA:2406","score":0.5022660042881579,"itemname":"Locked-in syndrome","rank":27.0},{"itemid":"ORPHA:101010","score":0.5010973520018859,"itemname":"Autosomal spastic paraplegia type 30","rank":28.0},{"itemid":"ORPHA:79135","score":0.5003191829243043,"itemname":"Episodic ataxia type 3","rank":29.5},{"itemid":"ORPHA:14","score":0.5003191829243043,"itemname":"Abetalipoproteinemia","rank":29.5},{"itemid":"ORPHA:139480","score":0.5,"itemname":"Autosomal recessive spastic paraplegia type 39","rank":31.0},{"itemid":"ORPHA:100994","score":0.4937419311010187,"itemname":"Autosomal dominant spastic paraplegia type 13","rank":32.0},{"itemid":"ORPHA:75374","score":0.48686449556014755,"itemname":"Bradyopsia","rank":33.0},{"itemid":"ORPHA:423275","score":0.48507125007266594,"itemname":"Spinocerebellar ataxia type 40","rank":34.0},{"itemid":"ORPHA:1186","score":0.48148148148148145,"itemname":"Infantile onset spinocerebellar ataxia","rank":35.0},{"itemid":"ORPHA:569","score":0.4811252243246881,"itemname":"Familial or sporadic hemiplegic migraine","rank":36.5},{"itemid":"ORPHA:2807","score":0.4811252243246881,"itemname":"Papilloma of choroid plexus","rank":36.5},{"itemid":"ORPHA:2826","score":0.48089047182263056,"itemname":"Spastic paraplegia-precocious puberty syndrome","rank":38.0},{"itemid":"ORPHA:101005","score":0.4803844614152614,"itemname":"Autosomal recessive spastic paraplegia type 25","rank":39.5},{"itemid":"ORPHA:1179","score":0.4803844614152614,"itemname":"Benign paroxysmal tonic upgaze of childhood with ataxia","rank":39.5},{"itemid":"ORPHA:320401","score":0.47740991602628857,"itemname":"Autosomal recessive spastic paraplegia type 44","rank":41.0},{"itemid":"ORPHA:401835","score":0.4751310967331989,"itemname":"Autosomal recessive spastic paraplegia type 70","rank":42.0},{"itemid":"ORPHA:209970","score":0.4745789978762495,"itemname":"Episodic ataxia type 7","rank":43.0},{"itemid":"ORPHA:459056","score":0.47377936967913425,"itemname":"Autosomal recessive spastic paraplegia type 75","rank":44.0},{"itemid":"ORPHA:1187","score":0.4702304105723988,"itemname":"Lethal ataxia with deafness and optic atrophy","rank":45.0},{"itemid":"ORPHA:101077","score":0.4643825309009521,"itemname":"X-linked Charcot-Marie-Tooth disease type 3","rank":46.5},{"itemid":"ORPHA:314911","score":0.4643825309009521,"itemname":"Severe Canavan disease","rank":46.5},{"itemid":"ORPHA:2608","score":0.46068221272042836,"itemname":"N syndrome","rank":48.0},{"itemid":"ORPHA:487","score":0.45923114679577626,"itemname":"Krabbe disease","rank":49.0},{"itemid":"ORPHA:845","score":0.4589913274017581,"itemname":"Tay-Sachs disease","rank":50.0}]},{"method":"Cosine Weighted Similarity","results":[{"itemid":"ORPHA:401795","score":0.6995052612605258,"itemname":"Autosomal recessive spastic paraplegia type 59","rank":1.0},{"itemid":"ORPHA:2818","score":0.6956655929999345,"itemname":"Spastic paraplegia-glaucoma-intellectual disability syndrome","rank":2.0},{"itemid":"ORPHA:1910","score":0.6828949506688442,"itemname":"Fetal iodine syndrome","rank":3.0},{"itemid":"ORPHA:101004","score":0.6743019308342771,"itemname":"Autosomal recessive spastic paraplegia type 24","rank":4.0},{"itemid":"ORPHA:466722","score":0.662891157970032,"itemname":"Autosomal recessive spastic paraplegia type 77","rank":5.0},{"itemid":"ORPHA:53583","score":0.662325765247424,"itemname":"Paroxysmal dystonic choreathetosis with episodic ataxia and spasticity","rank":6.0},{"itemid":"ORPHA:2815","score":0.6595945960564611,"itemname":"Spastic paraparesis-deafness syndrome","rank":7.0},{"itemid":"ORPHA:43","score":0.6427523858049926,"itemname":"X-linked adrenoleukodystrophy","rank":8.0},{"itemid":"ORPHA:464282","score":0.6379539109540315,"itemname":"Spastic paraplegia-severe developmental delay-epilepsy syndrome","rank":9.0},{"itemid":"ORPHA:251282","score":0.6338808574330934,"itemname":"Autosomal dominant spastic ataxia type 1","rank":10.0},{"itemid":"ORPHA:468661","score":0.6336998382696953,"itemname":"Autosomal recessive spastic paraplegia type 74","rank":11.0},{"itemid":"ORPHA:85336","score":0.629940788348712,"itemname":"X-linked neurodegenerative syndrome, Hamel type","rank":12.0},{"itemid":"ORPHA:329308","score":0.626378260496427,"itemname":"Fatty acid hydroxylase-associated neurodegeneration","rank":13.0},{"itemid":"ORPHA:13","score":0.6197218333201062,"itemname":"6-pyruvoyl-tetrahydropterin synthase deficiency","rank":14.0},{"itemid":"ORPHA:293168","score":0.6053501480489778,"itemname":"Infantile-onset ascending hereditary spastic paralysis","rank":15.0},{"itemid":"ORPHA:101010","score":0.5999176531250776,"itemname":"Autosomal spastic paraplegia type 30","rank":16.0},{"itemid":"ORPHA:320365","score":0.5985950469330272,"itemname":"Autosomal dominant spastic paraplegia type 36","rank":17.0},{"itemid":"ORPHA:171612","score":0.5977699942112389,"itemname":"Autosomal dominant spastic paraplegia type 37","rank":18.0},{"itemid":"ORPHA:569","score":0.5959135849024514,"itemname":"Familial or sporadic hemiplegic migraine","rank":19.0},{"itemid":"ORPHA:838","score":0.5915958148766435,"itemname":"Susac syndrome","rank":20.0},{"itemid":"ORPHA:401835","score":0.5818146428572329,"itemname":"Autosomal recessive spastic paraplegia type 70","rank":21.0},{"itemid":"ORPHA:352641","score":0.5806534764931515,"itemname":"Autosomal recessive cerebellar ataxia with late-onset spasticity","rank":22.0},{"itemid":"ORPHA:255","score":0.5802588531856594,"itemname":"Dopa-responsive dystonia","rank":23.0},{"itemid":"ORPHA:1949","score":0.5767808900874183,"itemname":"Benign familial neonatal epilepsy","rank":24.0},{"itemid":"ORPHA:2672","score":0.5756822030464636,"itemname":"Neuhauser-Eichner-Opitz syndrome","rank":25.0},{"itemid":"ORPHA:100994","score":0.5729810913102362,"itemname":"Autosomal dominant spastic paraplegia type 13","rank":26.0},{"itemid":"ORPHA:99735","score":0.572278193456637,"itemname":"Myotonia permanens","rank":27.0},{"itemid":"ORPHA:3137","score":0.5715347862488166,"itemname":"Alpha-N-acetylgalactosaminidase deficiency","rank":28.0},{"itemid":"ORPHA:401785","score":0.5709581829182253,"itemname":"Autosomal recessive spastic paraplegia type 62","rank":29.0},{"itemid":"ORPHA:401800","score":0.5695214286468868,"itemname":"Autosomal recessive spastic paraplegia type 60","rank":30.0},{"itemid":"ORPHA:3175","score":0.5657789498610036,"itemname":"X-linked spasticity-intellectual disability-epilepsy syndrome","rank":31.0},{"itemid":"ORPHA:459056","score":0.5654827907244966,"itemname":"Autosomal recessive spastic paraplegia type 75","rank":32.0},{"itemid":"ORPHA:506","score":0.5654612866967308,"itemname":"Leigh syndrome","rank":33.0},{"itemid":"ORPHA:685","score":0.5625300093854088,"itemname":"Hereditary spastic paraplegia","rank":34.0},{"itemid":"ORPHA:423275","score":0.5619514869490163,"itemname":"Spinocerebellar ataxia type 40","rank":35.0},{"itemid":"ORPHA:320360","score":0.5616282742022877,"itemname":"MT-ATP6-related mitochondrial spastic paraplegia","rank":36.0},{"itemid":"ORPHA:320355","score":0.5598833697790121,"itemname":"Autosomal dominant spastic paraplegia type 41","rank":37.0},{"itemid":"ORPHA:101005","score":0.5586611283331252,"itemname":"Autosomal recessive spastic paraplegia type 25","rank":38.0},{"itemid":"ORPHA:320380","score":0.555965574353193,"itemname":"Autosomal recessive spastic paraplegia type 54","rank":39.0},{"itemid":"ORPHA:157846","score":0.5525851045027059,"itemname":"Neuroferritinopathy","rank":40.0},{"itemid":"ORPHA:256","score":0.5477225575051661,"itemname":"Early-onset generalized limb-onset dystonia","rank":41.5},{"itemid":"ORPHA:79323","score":0.5477225575051661,"itemname":"MPDU1-CDG","rank":41.5},{"itemid":"ORPHA:1398","score":0.5465590229266869,"itemname":"Isolated cerebellar agenesis","rank":43.0},{"itemid":"ORPHA:79279","score":0.5461349395059337,"itemname":"Alpha-N-acetylgalactosaminidase deficiency type 1","rank":44.0},{"itemid":"ORPHA:2406","score":0.543580741049023,"itemname":"Locked-in syndrome","rank":45.0},{"itemid":"ORPHA:401953","score":0.5416710947332514,"itemname":"Episodic ataxia with slurred speech","rank":46.0},{"itemid":"ORPHA:2822","score":0.540767352545145,"itemname":"Autosomal recessive spastic paraplegia type 11","rank":47.0},{"itemid":"ORPHA:2820","score":0.5392332667218177,"itemname":"Spastic paraplegia-nephritis-deafness syndrome","rank":48.0},{"itemid":"ORPHA:254343","score":0.5391964695801414,"itemname":"Autosomal recessive spastic ataxia-optic atrophy-dysarthria syndrome","rank":49.0},{"itemid":"ORPHA:306511","score":0.5370414497943483,"itemname":"Autosomal recessive spastic paraplegia type 48","rank":50.0}]},{"method":"Jaccard standard","results":[{"itemid":"ORPHA:2818","score":0.5333333333333333,"itemname":"Spastic paraplegia-glaucoma-intellectual disability syndrome","rank":1.0},{"itemid":"ORPHA:101004","score":0.4878048780487805,"itemname":"Autosomal recessive spastic paraplegia type 24","rank":2.0},{"itemid":"ORPHA:85336","score":0.42105263157894735,"itemname":"X-linked neurodegenerative syndrome, Hamel type","rank":3.0},{"itemid":"ORPHA:1910","score":0.4090909090909091,"itemname":"Fetal iodine syndrome","rank":4.0},{"itemid":"ORPHA:53583","score":0.39622641509433965,"itemname":"Paroxysmal dystonic choreathetosis with episodic ataxia and spasticity","rank":5.0},{"itemid":"ORPHA:2815","score":0.39344262295081966,"itemname":"Spastic paraparesis-deafness syndrome","rank":6.0},{"itemid":"ORPHA:255","score":0.3793103448275862,"itemname":"Dopa-responsive dystonia","rank":7.0},{"itemid":"ORPHA:401795","score":0.375,"itemname":"Autosomal recessive spastic paraplegia type 59","rank":8.5},{"itemid":"ORPHA:293168","score":0.375,"itemname":"Infantile-onset ascending hereditary spastic paralysis","rank":8.5},{"itemid":"ORPHA:67047","score":0.37037037037037035,"itemname":"3-methylglutaconic aciduria type 3","rank":10.0},{"itemid":"ORPHA:101007","score":0.36666666666666664,"itemname":"Autosomal recessive spastic paraplegia type 27","rank":11.0},{"itemid":"ORPHA:685","score":0.36363636363636365,"itemname":"Hereditary spastic paraplegia","rank":12.0},{"itemid":"ORPHA:401800","score":0.36,"itemname":"Autosomal recessive spastic paraplegia type 60","rank":13.0},{"itemid":"ORPHA:217012","score":0.35185185185185186,"itemname":"Spinocerebellar ataxia type 31","rank":14.0},{"itemid":"ORPHA:506","score":0.3448275862068966,"itemname":"Leigh syndrome","rank":15.0},{"itemid":"ORPHA:3175","score":0.34285714285714286,"itemname":"X-linked spasticity-intellectual disability-epilepsy syndrome","rank":16.0},{"itemid":"ORPHA:85297","score":0.3404255319148936,"itemname":"X-linked spinocerebellar ataxia type 3","rank":17.5},{"itemid":"ORPHA:357043","score":0.3404255319148936,"itemname":"Amyotrophic lateral sclerosis type 4","rank":17.5},{"itemid":"ORPHA:256","score":0.3333333333333333,"itemname":"Early-onset generalized limb-onset dystonia","rank":20.5},{"itemid":"ORPHA:1949","score":0.3333333333333333,"itemname":"Benign familial neonatal epilepsy","rank":20.5},{"itemid":"ORPHA:79135","score":0.3333333333333333,"itemname":"Episodic ataxia type 3","rank":20.5},{"itemid":"ORPHA:14","score":0.3333333333333333,"itemname":"Abetalipoproteinemia","rank":20.5},{"itemid":"ORPHA:79323","score":0.3225806451612903,"itemname":"MPDU1-CDG","rank":23.0},{"itemid":"ORPHA:1368","score":0.31746031746031744,"itemname":"Cataract-ataxia-deafness syndrome","rank":24.0},{"itemid":"ORPHA:1186","score":0.3170731707317073,"itemname":"Infantile onset spinocerebellar ataxia","rank":25.0},{"itemid":"ORPHA:139480","score":0.3157894736842105,"itemname":"Autosomal recessive spastic paraplegia type 39","rank":26.0},{"itemid":"ORPHA:726","score":0.31343283582089554,"itemname":"Alpers-Huttenlocher syndrome","rank":27.0},{"itemid":"ORPHA:569","score":0.3125,"itemname":"Familial or sporadic hemiplegic migraine","rank":28.5},{"itemid":"ORPHA:2807","score":0.3125,"itemname":"Papilloma of choroid plexus","rank":28.5},{"itemid":"ORPHA:2406","score":0.3114754098360656,"itemname":"Locked-in syndrome","rank":30.0},{"itemid":"ORPHA:2822","score":0.3076923076923077,"itemname":"Autosomal recessive spastic paraplegia type 11","rank":31.5},{"itemid":"ORPHA:2826","score":0.3076923076923077,"itemname":"Spastic paraplegia-precocious puberty syndrome","rank":31.5},{"itemid":"ORPHA:209970","score":0.30612244897959184,"itemname":"Episodic ataxia type 7","rank":33.0},{"itemid":"ORPHA:101010","score":0.30303030303030304,"itemname":"Autosomal spastic paraplegia type 30","rank":34.0},{"itemid":"ORPHA:401835","score":0.3018867924528302,"itemname":"Autosomal recessive spastic paraplegia type 70","rank":35.0},{"itemid":"ORPHA:401830","score":0.3,"itemname":"Autosomal recessive spastic paraplegia type 69","rank":36.5},{"itemid":"ORPHA:423275","score":0.3,"itemname":"Spinocerebellar ataxia type 40","rank":36.5},{"itemid":"ORPHA:3011","score":0.29545454545454547,"itemname":"Spastic tetraplegia-retinitis pigmentosa-intellectual disability syndrome","rank":38.0},{"itemid":"ORPHA:101005","score":0.29508196721311475,"itemname":"Autosomal recessive spastic paraplegia type 25","rank":39.0},{"itemid":"ORPHA:3233","score":0.2926829268292683,"itemname":"Cochleosaccular degeneration-cataract syndrome","rank":40.5},{"itemid":"ORPHA:2940","score":0.2926829268292683,"itemname":"Porencephaly","rank":40.5},{"itemid":"ORPHA:1917","score":0.2916666666666667,"itemname":"Fetal methylmercury syndrome","rank":42.0},{"itemid":"ORPHA:1179","score":0.2903225806451613,"itemname":"Benign paroxysmal tonic upgaze of childhood with ataxia","rank":43.0},{"itemid":"ORPHA:100994","score":0.2876712328767123,"itemname":"Autosomal dominant spastic paraplegia type 13","rank":44.0},{"itemid":"ORPHA:2819","score":0.2857142857142857,"itemname":"Spastic paraplegia-facial-cutaneous lesions syndrome","rank":45.0},{"itemid":"ORPHA:3177","score":0.27906976744186046,"itemname":"Spinocerebellar degeneration-corneal dystrophy syndrome","rank":46.0},{"itemid":"ORPHA:2148","score":0.2777777777777778,"itemname":"Lissencephaly type 1 due to doublecortin gene mutation","rank":47.5},{"itemid":"ORPHA:320401","score":0.2777777777777778,"itemname":"Autosomal recessive spastic paraplegia type 44","rank":47.5},{"itemid":"ORPHA:75374","score":0.27586206896551724,"itemname":"Bradyopsia","rank":49.0},{"itemid":"ORPHA:1178","score":0.27450980392156865,"itemname":"Ataxia-tapetoretinal degeneration syndrome","rank":50.0}]},{"method":"Jaccard weighted","results":[{"itemid":"ORPHA:2818","score":0.45161290322580644,"itemname":"Spastic paraplegia-glaucoma-intellectual disability syndrome","rank":1.0},{"itemid":"ORPHA:1910","score":0.4510166358595194,"itemname":"Fetal iodine syndrome","rank":2.0},{"itemid":"ORPHA:101004","score":0.4454022988505747,"itemname":"Autosomal recessive spastic paraplegia type 24","rank":3.0},{"itemid":"ORPHA:401795","score":0.4312908982748364,"itemname":"Autosomal recessive spastic paraplegia type 59","rank":4.0},{"itemid":"ORPHA:2815","score":0.4179174484052533,"itemname":"Spastic paraparesis-deafness syndrome","rank":5.0},{"itemid":"ORPHA:85336","score":0.4166666666666667,"itemname":"X-linked neurodegenerative syndrome, Hamel type","rank":6.0},{"itemid":"ORPHA:293168","score":0.3918918918918919,"itemname":"Infantile-onset ascending hereditary spastic paralysis","rank":7.0},{"itemid":"ORPHA:43","score":0.3847583643122677,"itemname":"X-linked adrenoleukodystrophy","rank":8.0},{"itemid":"ORPHA:101010","score":0.36534926470588236,"itemname":"Autosomal spastic paraplegia type 30","rank":9.0},{"itemid":"ORPHA:251282","score":0.3581593927893738,"itemname":"Autosomal dominant spastic ataxia type 1","rank":10.0},{"itemid":"ORPHA:466722","score":0.3575517393218846,"itemname":"Autosomal recessive spastic paraplegia type 77","rank":11.0},{"itemid":"ORPHA:171612","score":0.3525954946131244,"itemname":"Autosomal dominant spastic paraplegia type 37","rank":12.0},{"itemid":"ORPHA:468661","score":0.3511777301927195,"itemname":"Autosomal recessive spastic paraplegia type 74","rank":13.0},{"itemid":"ORPHA:320365","score":0.3447951012717852,"itemname":"Autosomal dominant spastic paraplegia type 36","rank":14.0},{"itemid":"ORPHA:53583","score":0.34278959810874704,"itemname":"Paroxysmal dystonic choreathetosis with episodic ataxia and spasticity","rank":15.0},{"itemid":"ORPHA:329308","score":0.3394255874673629,"itemname":"Fatty acid hydroxylase-associated neurodegeneration","rank":16.0},{"itemid":"ORPHA:685","score":0.33872901678657075,"itemname":"Hereditary spastic paraplegia","rank":17.0},{"itemid":"ORPHA:2822","score":0.3379224030037547,"itemname":"Autosomal recessive spastic paraplegia type 11","rank":18.0},{"itemid":"ORPHA:506","score":0.3365617433414044,"itemname":"Leigh syndrome","rank":19.0},{"itemid":"ORPHA:459056","score":0.3342904019688269,"itemname":"Autosomal recessive spastic paraplegia type 75","rank":20.0},{"itemid":"ORPHA:85297","score":0.3333333333333333,"itemname":"X-linked spinocerebellar ataxia type 3","rank":21.5},{"itemid":"ORPHA:3175","score":0.3333333333333333,"itemname":"X-linked spasticity-intellectual disability-epilepsy syndrome","rank":21.5},{"itemid":"ORPHA:320355","score":0.3302752293577982,"itemname":"Autosomal dominant spastic paraplegia type 41","rank":23.0},{"itemid":"ORPHA:100994","score":0.3277027027027027,"itemname":"Autosomal dominant spastic paraplegia type 13","rank":24.0},{"itemid":"ORPHA:320360","score":0.32432432432432434,"itemname":"MT-ATP6-related mitochondrial spastic paraplegia","rank":25.0},{"itemid":"ORPHA:255","score":0.3225806451612903,"itemname":"Dopa-responsive dystonia","rank":26.0},{"itemid":"ORPHA:101007","score":0.32169459962756053,"itemname":"Autosomal recessive spastic paraplegia type 27","rank":27.0},{"itemid":"ORPHA:2820","score":0.31985784095957354,"itemname":"Spastic paraplegia-nephritis-deafness syndrome","rank":28.0},{"itemid":"ORPHA:2672","score":0.3156887755102041,"itemname":"Neuhauser-Eichner-Opitz syndrome","rank":29.0},{"itemid":"ORPHA:464282","score":0.3139249386180288,"itemname":"Spastic paraplegia-severe developmental delay-epilepsy syndrome","rank":30.0},{"itemid":"ORPHA:2406","score":0.3138014527845036,"itemname":"Locked-in syndrome","rank":31.0},{"itemid":"ORPHA:1171","score":0.3102362204724409,"itemname":"Cerebellar ataxia-areflexia-pes cavus-optic atrophy-sensorineural hearing loss syndrome","rank":32.0},{"itemid":"ORPHA:1187","score":0.30927835051546393,"itemname":"Lethal ataxia with deafness and optic atrophy","rank":33.0},{"itemid":"ORPHA:320401","score":0.30827702702702703,"itemname":"Autosomal recessive spastic paraplegia type 44","rank":34.0},{"itemid":"ORPHA:209970","score":0.3068720379146919,"itemname":"Episodic ataxia type 7","rank":35.0},{"itemid":"ORPHA:101077","score":0.30456171735241505,"itemname":"X-linked Charcot-Marie-Tooth disease type 3","rank":36.0},{"itemid":"ORPHA:352641","score":0.3041070604522381,"itemname":"Autosomal recessive cerebellar ataxia with late-onset spasticity","rank":37.0},{"itemid":"ORPHA:101005","score":0.30220994475138124,"itemname":"Autosomal recessive spastic paraplegia type 25","rank":38.0},{"itemid":"ORPHA:100988","score":0.30053428317008013,"itemname":"Autosomal dominant spastic paraplegia type 6","rank":39.0},{"itemid":"ORPHA:254343","score":0.29904306220095694,"itemname":"Autosomal recessive spastic ataxia-optic atrophy-dysarthria syndrome","rank":40.0},{"itemid":"ORPHA:1949","score":0.29867256637168144,"itemname":"Benign familial neonatal epilepsy","rank":41.0},{"itemid":"ORPHA:157846","score":0.29770565193060994,"itemname":"Neuroferritinopathy","rank":42.0},{"itemid":"ORPHA:79135","score":0.2975517890772128,"itemname":"Episodic ataxia type 3","rank":43.0},{"itemid":"ORPHA:799","score":0.29683698296836986,"itemname":"Schizencephaly","rank":44.0},{"itemid":"ORPHA:171863","score":0.29666254635352285,"itemname":"Autosomal dominant spastic paraplegia type 42","rank":45.0},{"itemid":"ORPHA:1368","score":0.2965235173824131,"itemname":"Cataract-ataxia-deafness syndrome","rank":46.0},{"itemid":"ORPHA:100989","score":0.29434250764525993,"itemname":"Autosomal dominant spastic paraplegia type 8","rank":47.0},{"itemid":"ORPHA:306511","score":0.29381846635367764,"itemname":"Autosomal recessive spastic paraplegia type 48","rank":48.0},{"itemid":"ORPHA:1398","score":0.29295774647887324,"itemname":"Isolated cerebellar agenesis","rank":49.0},{"itemid":"ORPHA:79279","score":0.29280948851000743,"itemname":"Alpha-N-acetylgalactosaminidase deficiency type 1","rank":50.0}]},{"method":"Phenodigm Similarity","results":[{"itemid":"ORPHA:2818","score":0.8189365817914082,"itemname":"Spastic paraplegia-glaucoma-intellectual disability syndrome","rank":1.0},{"itemid":"ORPHA:101004","score":0.8161008305650587,"itemname":"Autosomal recessive spastic paraplegia type 24","rank":2.0},{"itemid":"ORPHA:401800","score":0.7918240014493925,"itemname":"Autosomal recessive spastic paraplegia type 60","rank":3.0},{"itemid":"ORPHA:685","score":0.7881685201225601,"itemname":"Hereditary spastic paraplegia","rank":4.0},{"itemid":"ORPHA:401795","score":0.7845022477033705,"itemname":"Autosomal recessive spastic paraplegia type 59","rank":5.0},{"itemid":"ORPHA:293168","score":0.7834035360493434,"itemname":"Infantile-onset ascending hereditary spastic paralysis","rank":6.0},{"itemid":"ORPHA:101007","score":0.7746498302244159,"itemname":"Autosomal recessive spastic paraplegia type 27","rank":7.0},{"itemid":"ORPHA:139480","score":0.7669302164264739,"itemname":"Autosomal recessive spastic paraplegia type 39","rank":8.0},{"itemid":"ORPHA:459056","score":0.757218383053356,"itemname":"Autosomal recessive spastic paraplegia type 75","rank":9.0},{"itemid":"ORPHA:101010","score":0.7540634421443883,"itemname":"Autosomal spastic paraplegia type 30","rank":10.0},{"itemid":"ORPHA:53583","score":0.7538688241024288,"itemname":"Paroxysmal dystonic choreathetosis with episodic ataxia and spasticity","rank":11.0},{"itemid":"ORPHA:251282","score":0.750999666010574,"itemname":"Autosomal dominant spastic ataxia type 1","rank":12.0},{"itemid":"ORPHA:401830","score":0.7454141780597504,"itemname":"Autosomal recessive spastic paraplegia type 69","rank":13.0},{"itemid":"ORPHA:320396","score":0.7443673703773437,"itemname":"Autosomal recessive spastic paraplegia type 45","rank":14.0},{"itemid":"ORPHA:100994","score":0.7372447459865669,"itemname":"Autosomal dominant spastic paraplegia type 13","rank":15.0},{"itemid":"ORPHA:357043","score":0.7348341325774994,"itemname":"Amyotrophic lateral sclerosis type 4","rank":16.0},{"itemid":"ORPHA:506","score":0.7332400282451612,"itemname":"Leigh syndrome","rank":17.0},{"itemid":"ORPHA:209967","score":0.7295696195410284,"itemname":"Episodic ataxia type 6","rank":18.0},{"itemid":"ORPHA:100986","score":0.7273119201979604,"itemname":"Autosomal recessive spastic paraplegia type 5A","rank":19.0},{"itemid":"ORPHA:401840","score":0.7224788140297227,"itemname":"Autosomal recessive spastic paraplegia type 71","rank":20.0},{"itemid":"ORPHA:506353","score":0.7223956751561658,"itemname":"Autosomal recessive complex spastic paraplegia due to Kennedy pathway dysfunction","rank":21.0},{"itemid":"ORPHA:2822","score":0.7220645051092122,"itemname":"Autosomal recessive spastic paraplegia type 11","rank":22.0},{"itemid":"ORPHA:320355","score":0.7217439780600271,"itemname":"Autosomal dominant spastic paraplegia type 41","rank":23.0},{"itemid":"ORPHA:100989","score":0.720788182322722,"itemname":"Autosomal dominant spastic paraplegia type 8","rank":24.0},{"itemid":"ORPHA:171863","score":0.7200596366317574,"itemname":"Autosomal dominant spastic paraplegia type 42","rank":25.0},{"itemid":"ORPHA:726","score":0.7170681773400063,"itemname":"Alpers-Huttenlocher syndrome","rank":26.0},{"itemid":"ORPHA:431329","score":0.715027224913742,"itemname":"Autosomal recessive spastic paraplegia type 57","rank":27.0},{"itemid":"ORPHA:2819","score":0.7066026705972062,"itemname":"Spastic paraplegia-facial-cutaneous lesions syndrome","rank":28.0},{"itemid":"ORPHA:401815","score":0.7063024879557777,"itemname":"Autosomal recessive spastic paraplegia type 66","rank":29.0},{"itemid":"ORPHA:320411","score":0.7061878677214575,"itemname":"Autosomal recessive spastic paraplegia type 56","rank":30.0},{"itemid":"ORPHA:444099","score":0.7061598147251622,"itemname":"Autosomal dominant spastic paraplegia type 73","rank":31.0},{"itemid":"ORPHA:329308","score":0.7056708348467677,"itemname":"Fatty acid hydroxylase-associated neurodegeneration","rank":32.0},{"itemid":"ORPHA:401820","score":0.7053464341735926,"itemname":"Autosomal recessive spastic paraplegia type 67","rank":33.0},{"itemid":"ORPHA:2820","score":0.7041515718080703,"itemname":"Spastic paraplegia-nephritis-deafness syndrome","rank":34.0},{"itemid":"ORPHA:1891","score":0.7010827154997846,"itemname":"Intellectual disability-spasticity-ectrodactyly syndrome","rank":35.0},{"itemid":"ORPHA:401835","score":0.6975997208513636,"itemname":"Autosomal recessive spastic paraplegia type 70","rank":36.0},{"itemid":"ORPHA:85336","score":0.6974024652949979,"itemname":"X-linked neurodegenerative syndrome, Hamel type","rank":37.0},{"itemid":"ORPHA:306511","score":0.6970604739082148,"itemname":"Autosomal recessive spastic paraplegia type 48","rank":38.0},{"itemid":"ORPHA:98673","score":0.6961016646479208,"itemname":"Autosomal dominant optic atrophy, classic form","rank":39.0},{"itemid":"ORPHA:139578","score":0.6959880359033037,"itemname":"Mutilating hereditary sensory neuropathy with spastic paraplegia","rank":40.0},{"itemid":"ORPHA:2821","score":0.6959197768364933,"itemname":"Spastic paraplegia-neuropathy-poikiloderma syndrome","rank":41.0},{"itemid":"ORPHA:100988","score":0.6955606612457289,"itemname":"Autosomal dominant spastic paraplegia type 6","rank":42.0},{"itemid":"ORPHA:2826","score":0.692925884934853,"itemname":"Spastic paraplegia-precocious puberty syndrome","rank":43.0},{"itemid":"ORPHA:513436","score":0.6922809600080393,"itemname":"Autosomal recessive spastic paraplegia type 78","rank":44.0},{"itemid":"ORPHA:171622","score":0.6900896514222186,"itemname":"Autosomal recessive spastic paraplegia type 32","rank":45.0},{"itemid":"ORPHA:320380","score":0.6899163378481699,"itemname":"Autosomal recessive spastic paraplegia type 54","rank":46.0},{"itemid":"ORPHA:171612","score":0.6896350889343236,"itemname":"Autosomal dominant spastic paraplegia type 37","rank":47.0},{"itemid":"ORPHA:2815","score":0.6877143522299309,"itemname":"Spastic paraparesis-deafness syndrome","rank":48.0},{"itemid":"ORPHA:101005","score":0.686262232804965,"itemname":"Autosomal recessive spastic paraplegia type 25","rank":49.0},{"itemid":"ORPHA:2466","score":0.6858739174157474,"itemname":"MASA syndrome","rank":50.0}]}],"ontology-version":"hp\/releases\/2019-06-03"}